tidypolars4sci/#tibble_df.py#
tidypolars4sci/__init__.py
tidypolars4sci/funs.py
tidypolars4sci/helpers.py
tidypolars4sci/io.py
tidypolars4sci/lubridate.py
tidypolars4sci/reexports.py
tidypolars4sci/stats.py
tidypolars4sci/stringr.py
tidypolars4sci/tibble_df.py
tidypolars4sci/type_conversion.py
tidypolars4sci/utils.py
tidypolars4sci/data/__init__.py
tidypolars4sci/data/diamonds.csv
tidypolars4sci/data/diamonds.py
tidypolars4sci/data/mtcars.csv
tidypolars4sci/data/mtcars.py
tidypolars4sci/data/starwars.py
tidypolars4sci/data/starwars.rda
tidypolars4sci/data/vote.csv
tidypolars4sci/data/vote.py
tidypolars4sci-0.0.1.22.dist-info/METADATA
tidypolars4sci-0.0.1.22.dist-info/WHEEL
tidypolars4sci-0.0.1.22.dist-info/licenses/LICENSE
tidypolars4sci-0.0.1.22.dist-info/RECORD
