Metadata-Version: 2.4
Name: tidypolars4sci
Version: 0.0.1.22
Summary: Tidyverse-like functions for python polars with extended functionalities for science.
Project-URL: Homepage, https://github.com/DiogoFerrari/tidypolars4sci
Project-URL: Documentation, https://github.com/DiogoFerrari/tidypolars4sci
Project-URL: Changelog, https://github.com/DiogoFerrari/tidypolars4sci/blob/master/CHANGELOG.md
Project-URL: Issues, https://github.com/DiogoFerrari/tidypolars4sci/issues/
Author-email: Diogo Ferrari <diogoferrari@gmail.com>
Maintainer-email: Diogo Ferrari <diogoferrari@gmail.com>
License-Expression: MIT
License-File: LICENSE
Keywords: dataframe,polars,tidy data,tidyverse
Classifier: Development Status :: 4 - Beta
Classifier: Intended Audience :: Science/Research
Classifier: Topic :: Scientific/Engineering
Requires-Python: >=3.6
Requires-Dist: numpy
Requires-Dist: pandas
Requires-Dist: polars
Requires-Dist: pyarrow
Requires-Dist: pyreadr
Requires-Dist: pyreadstat
